pysapscript/__init__.py
pysapscript/pysapscript.py
pysapscript/shell_table.py
pysapscript/shell_tree.py
pysapscript/window.py
pysapscript/types_/__init__.py
pysapscript/types_/exceptions.py
pysapscript/types_/types.py
pysapscript/utils/__init__.py
pysapscript/utils/utils.py
pysapscript-3.7.0.dist-info/METADATA
pysapscript-3.7.0.dist-info/WHEEL
pysapscript-3.7.0.dist-info/licenses/licence.txt
pysapscript-3.7.0.dist-info/RECORD
