Metadata-Version: 2.4
Name: pysapscript
Version: 3.7.0
Summary: Automate SAP with python!
Author-email: Kamil Democko <democko_kamil@vseholding.sk>
License-File: licence.txt
Requires-Python: >=3.10
Requires-Dist: pandas>=2.2.3
Requires-Dist: polars>=1.30.0
Requires-Dist: pyarrow>=20.0.0
Requires-Dist: pywin32>=310
